{
  "view": "Range Setup",
  "summary": "Price action view generated as lightweight JSON. Use this to display trend, support, resistance, zones and risk levels without loading a heavy image.",
  "symbol": "ITC",
  "stockName": "ITC Ltd",
  "updatedAt": "24-Jun-2026 17:07 IST",
  "metrics": [
    {
      "label": "Trend",
      "value": "Weak Bias"
    },
    {
      "label": "Trend Strength",
      "value": "ADX 19.0 (Moderate)"
    },
    {
      "label": "Structure",
      "value": "Mixed/Range"
    },
    {
      "label": "Volume",
      "value": "Normal (Z: -1.19)"
    }
  ],
  "levels": [
    {
      "label": "Close",
      "value": 290.3500061035156,
      "type": "price"
    },
    {
      "label": "EMA20",
      "value": 289.9974588005746,
      "type": "price"
    },
    {
      "label": "EMA50",
      "value": 296.3058022794377,
      "type": "price"
    },
    {
      "label": "ATR",
      "value": 4.5949267928707505,
      "type": "price"
    },
    {
      "label": "Support",
      "value": "₹275.05"
    },
    {
      "label": "Resistance",
      "value": "₹317.90"
    },
    {
      "label": "Buy Zone",
      "value": "₹275.51 → ₹277.81"
    },
    {
      "label": "Sell Zone",
      "value": "₹315.14 → ₹317.44"
    },
    {
      "label": "Stop Loss",
      "value": "₹270.46"
    }
  ],
  "rows": [
    {
      "label": "Risk View",
      "value": "Avoid fresh entry in middle zone"
    },
    {
      "label": "Action View",
      "value": "Wait for confirmation near support or breakout zone"
    },
    {
      "label": "Best Use",
      "value": "Range setup planning"
    }
  ],
  "note": "Educational research view only. Not investment advice.",
  "source": "GeneratePriceActionJson.py"
}