{
  "view": "Weak / Wait Zone",
  "summary": "Technical analysis view with trend, RSI, volume, support/resistance and action zones rendered from JSON.",
  "symbol": "BAJAJ-AUTO",
  "stockName": "Bajaj Auto Ltd.",
  "updatedAt": "01-Jul-2026 02:03 IST",
  "metrics": [
    {
      "label": "Trend",
      "value": "Bearish"
    },
    {
      "label": "Signal",
      "value": "Weak / Wait Zone"
    },
    {
      "label": "1D Move",
      "value": -2.16,
      "type": "percent"
    },
    {
      "label": "RSI",
      "value": "34.30"
    },
    {
      "label": "ADX",
      "value": "20.6"
    },
    {
      "label": "Volume",
      "value": "Normal (Z: 0.75)"
    }
  ],
  "levels": [
    {
      "label": "Close",
      "value": 9630.0,
      "type": "price"
    },
    {
      "label": "EMA9",
      "value": 9893.838412449508,
      "type": "price"
    },
    {
      "label": "EMA21",
      "value": 10037.917091421223,
      "type": "price"
    },
    {
      "label": "EMA50",
      "value": 10039.471987648214,
      "type": "price"
    },
    {
      "label": "Support",
      "value": 8755.0,
      "type": "price"
    },
    {
      "label": "Resistance",
      "value": 10834.0,
      "type": "price"
    },
    {
      "label": "Buy Zone",
      "value": "₹8,755.00 → ₹8,848.43"
    },
    {
      "label": "Sell / Target",
      "value": "₹10,834.00"
    },
    {
      "label": "Stop Loss",
      "value": "₹8,640.81"
    }
  ],
  "rows": [
    {
      "label": "Chart Mood",
      "value": "Weak setup; wait for confirmation"
    },
    {
      "label": "Risk Note",
      "value": "Respect stop-loss if breakdown continues"
    },
    {
      "label": "Best Use",
      "value": "Technical zone reference"
    }
  ],
  "source": "GenerateTechnicalAnalysisJson.py",
  "sourceNote": "Educational technical research view only. Not investment advice."
}