{
  "view": "Support Test / Caution",
  "summary": "Technical analysis view with trend, RSI, volume, support/resistance and action zones rendered from JSON.",
  "symbol": "COALINDIA",
  "stockName": "Coal India Ltd.",
  "updatedAt": "06-Jul-2026 18:47 IST",
  "metrics": [
    {
      "label": "Trend",
      "value": "Bearish"
    },
    {
      "label": "Signal",
      "value": "Support Test / Caution"
    },
    {
      "label": "1D Move",
      "value": -1.45,
      "type": "percent"
    },
    {
      "label": "RSI",
      "value": "37.14"
    },
    {
      "label": "ADX",
      "value": "13.7"
    },
    {
      "label": "Volume",
      "value": "Normal (Z: -0.30)"
    }
  ],
  "levels": [
    {
      "label": "Close",
      "value": 432.3500061035156,
      "type": "price"
    },
    {
      "label": "EMA9",
      "value": 438.9123602321842,
      "type": "price"
    },
    {
      "label": "EMA21",
      "value": 445.0936405695644,
      "type": "price"
    },
    {
      "label": "EMA50",
      "value": 450.20028487352556,
      "type": "price"
    },
    {
      "label": "Support",
      "value": 428.3999938964844,
      "type": "price"
    },
    {
      "label": "Resistance",
      "value": 484.45001220703125,
      "type": "price"
    },
    {
      "label": "Buy Zone",
      "value": "₹428.40 → ₹432.61"
    },
    {
      "label": "Sell / Target",
      "value": "₹484.45"
    },
    {
      "label": "Stop Loss",
      "value": "₹423.25"
    }
  ],
  "rows": [
    {
      "label": "Chart Mood",
      "value": "Weak setup; wait for confirmation"
    },
    {
      "label": "Risk Note",
      "value": "Respect stop-loss if breakdown continues"
    },
    {
      "label": "Best Use",
      "value": "Technical zone reference"
    }
  ],
  "source": "GenerateTechnicalAnalysisJson.py",
  "sourceNote": "Educational technical research view only. Not investment advice."
}