{
  "view": "Overbought / Avoid Chase",
  "summary": "Technical analysis view with trend, RSI, volume, support/resistance and action zones rendered from JSON.",
  "symbol": "DRREDDY",
  "stockName": "Dr. Reddy's Laboratories Ltd.",
  "updatedAt": "01-Jul-2026 02:03 IST",
  "metrics": [
    {
      "label": "Trend",
      "value": "Bullish"
    },
    {
      "label": "Signal",
      "value": "Overbought / Avoid Chase"
    },
    {
      "label": "1D Move",
      "value": 1.87,
      "type": "percent"
    },
    {
      "label": "RSI",
      "value": "74.51"
    },
    {
      "label": "ADX",
      "value": "23.1"
    },
    {
      "label": "Volume",
      "value": "Surge (Z: 3.96)"
    }
  ],
  "levels": [
    {
      "label": "Close",
      "value": 1375.699951171875,
      "type": "price"
    },
    {
      "label": "EMA9",
      "value": 1325.298046346662,
      "type": "price"
    },
    {
      "label": "EMA21",
      "value": 1305.9515799496894,
      "type": "price"
    },
    {
      "label": "EMA50",
      "value": 1294.472357965974,
      "type": "price"
    },
    {
      "label": "Support",
      "value": 1248.4000244140625,
      "type": "price"
    },
    {
      "label": "Resistance",
      "value": 1414.9000244140625,
      "type": "price"
    },
    {
      "label": "Buy Zone",
      "value": "₹1,248.40 → ₹1,261.03"
    },
    {
      "label": "Sell / Target",
      "value": "₹1,414.90"
    },
    {
      "label": "Stop Loss",
      "value": "₹1,232.97"
    }
  ],
  "rows": [
    {
      "label": "Chart Mood",
      "value": "Positive setup; avoid chasing extended moves"
    },
    {
      "label": "Risk Note",
      "value": "Respect support if momentum weakens"
    },
    {
      "label": "Best Use",
      "value": "Technical zone reference"
    }
  ],
  "source": "GenerateTechnicalAnalysisJson.py",
  "sourceNote": "Educational technical research view only. Not investment advice."
}