{
  "view": "Weak / Wait Zone",
  "summary": "Technical analysis view with trend, RSI, volume, support/resistance and action zones rendered from JSON.",
  "symbol": "POWERGRID",
  "stockName": "Power Grid Corporation of India Ltd",
  "updatedAt": "01-Jul-2026 02:03 IST",
  "metrics": [
    {
      "label": "Trend",
      "value": "Bearish"
    },
    {
      "label": "Signal",
      "value": "Weak / Wait Zone"
    },
    {
      "label": "1D Move",
      "value": 0.83,
      "type": "percent"
    },
    {
      "label": "RSI",
      "value": "43.62"
    },
    {
      "label": "ADX",
      "value": "18.6"
    },
    {
      "label": "Volume",
      "value": "Elevated (Z: 1.65)"
    }
  ],
  "levels": [
    {
      "label": "Close",
      "value": 286.25,
      "type": "price"
    },
    {
      "label": "EMA9",
      "value": 287.2152493463726,
      "type": "price"
    },
    {
      "label": "EMA21",
      "value": 289.16128146651414,
      "type": "price"
    },
    {
      "label": "EMA50",
      "value": 293.63729654396144,
      "type": "price"
    },
    {
      "label": "Support",
      "value": 278.3999938964844,
      "type": "price"
    },
    {
      "label": "Resistance",
      "value": 308.1499938964844,
      "type": "price"
    },
    {
      "label": "Buy Zone",
      "value": "₹278.40 → ₹280.87"
    },
    {
      "label": "Sell / Target",
      "value": "₹308.15"
    },
    {
      "label": "Stop Loss",
      "value": "₹275.38"
    }
  ],
  "rows": [
    {
      "label": "Chart Mood",
      "value": "Weak setup; wait for confirmation"
    },
    {
      "label": "Risk Note",
      "value": "Respect stop-loss if breakdown continues"
    },
    {
      "label": "Best Use",
      "value": "Technical zone reference"
    }
  ],
  "source": "GenerateTechnicalAnalysisJson.py",
  "sourceNote": "Educational technical research view only. Not investment advice."
}