{
  "view": "Weak / Wait Zone",
  "summary": "Technical analysis view with trend, RSI, volume, support/resistance and action zones rendered from JSON.",
  "symbol": "SBILIFE",
  "stockName": "SBI Life Insurance Company Ltd.",
  "updatedAt": "29-Jun-2026 22:23 IST",
  "metrics": [
    {
      "label": "Trend",
      "value": "Bearish"
    },
    {
      "label": "Signal",
      "value": "Weak / Wait Zone"
    },
    {
      "label": "1D Move",
      "value": 0.6,
      "type": "percent"
    },
    {
      "label": "RSI",
      "value": "41.98"
    },
    {
      "label": "ADX",
      "value": "19.9"
    },
    {
      "label": "Volume",
      "value": "Surge (Z: 3.76)"
    }
  ],
  "levels": [
    {
      "label": "Close",
      "value": 1755.4000244140625,
      "type": "price"
    },
    {
      "label": "EMA9",
      "value": 1770.4637056255492,
      "type": "price"
    },
    {
      "label": "EMA21",
      "value": 1784.2071070018947,
      "type": "price"
    },
    {
      "label": "EMA50",
      "value": 1820.7718812297835,
      "type": "price"
    },
    {
      "label": "Support",
      "value": 1700.4000244140625,
      "type": "price"
    },
    {
      "label": "Resistance",
      "value": 1906.9000244140625,
      "type": "price"
    },
    {
      "label": "Buy Zone",
      "value": "₹1,700.40 → ₹1,717.13"
    },
    {
      "label": "Sell / Target",
      "value": "₹1,906.90"
    },
    {
      "label": "Stop Loss",
      "value": "₹1,679.96"
    }
  ],
  "rows": [
    {
      "label": "Chart Mood",
      "value": "Weak setup; wait for confirmation"
    },
    {
      "label": "Risk Note",
      "value": "Respect stop-loss if breakdown continues"
    },
    {
      "label": "Best Use",
      "value": "Technical zone reference"
    }
  ],
  "source": "GenerateTechnicalAnalysisJson.py",
  "sourceNote": "Educational technical research view only. Not investment advice."
}