{
  "view": "Weak / Wait Zone",
  "summary": "Technical analysis view with trend, RSI, volume, support/resistance and action zones rendered from JSON.",
  "symbol": "SWIGGY",
  "stockName": "Swiggy Ltd.",
  "updatedAt": "03-Jul-2026 19:14 IST",
  "metrics": [
    {
      "label": "Trend",
      "value": "Weak"
    },
    {
      "label": "Signal",
      "value": "Weak / Wait Zone"
    },
    {
      "label": "1D Move",
      "value": -0.29,
      "type": "percent"
    },
    {
      "label": "RSI",
      "value": "47.65"
    },
    {
      "label": "ADX",
      "value": "14.1"
    },
    {
      "label": "Volume",
      "value": "Normal (Z: -0.25)"
    }
  ],
  "levels": [
    {
      "label": "Close",
      "value": 248.27000427246094,
      "type": "price"
    },
    {
      "label": "EMA9",
      "value": 246.30702216830363,
      "type": "price"
    },
    {
      "label": "EMA21",
      "value": 248.90946680476486,
      "type": "price"
    },
    {
      "label": "EMA50",
      "value": 258.23211994055794,
      "type": "price"
    },
    {
      "label": "Support",
      "value": 235.75,
      "type": "price"
    },
    {
      "label": "Resistance",
      "value": 272.29998779296875,
      "type": "price"
    },
    {
      "label": "Buy Zone",
      "value": "₹235.75 → ₹239.34"
    },
    {
      "label": "Sell / Target",
      "value": "₹272.30"
    },
    {
      "label": "Stop Loss",
      "value": "₹231.36"
    }
  ],
  "rows": [
    {
      "label": "Chart Mood",
      "value": "Weak setup; wait for confirmation"
    },
    {
      "label": "Risk Note",
      "value": "Respect stop-loss if breakdown continues"
    },
    {
      "label": "Best Use",
      "value": "Technical zone reference"
    }
  ],
  "source": "GenerateTechnicalAnalysisJson.py",
  "sourceNote": "Educational technical research view only. Not investment advice."
}