{
  "toolName": "Bullish/Bearish Momentum Scanner",
  "updatedAt": "13-Jul-2026 17:20 IST",
  "generatedAt": "13-Jul-2026 17:25 IST",
  "universeCount": 218,
  "signalCount": 73,
  "sourceNote": "Generated from AIT Stock Strength Ranker and existing 52-week high-low JSON files. Signals use daily move, strength score and 52-week position. Educational use only.",
  "stocks": [
    {
      "symbol": "BHEL",
      "stockName": "Bharat Heavy Electricals Ltd.",
      "indices": [
        "NIFTY ENERGY",
        "NIFTY MIDCAP 50"
      ],
      "cmp": 409.1,
      "changePct": 3.5,
      "downFromHighPct": -3.72,
      "aboveLowPct": 99.44,
      "strengthScore": 92.4,
      "momentumScore": 99.4,
      "bias": "Bullish Momentum",
      "rank": 1
    },
    {
      "symbol": "AEGISLOG",
      "stockName": "Aegis Logistics Ltd.",
      "indices": [
        "NIFTY ENERGY"
      ],
      "cmp": 1293.6,
      "changePct": 3.81,
      "downFromHighPct": -9.13,
      "aboveLowPct": 124.54,
      "strengthScore": 88.5,
      "momentumScore": 96.1,
      "bias": "Bullish Momentum",
      "rank": 2
    },
    {
      "symbol": "PFOCUS",
      "stockName": "Prime Focus Ltd.",
      "indices": [
        "NIFTY MEDIA"
      ],
      "cmp": 269.52,
      "changePct": 5.0,
      "downFromHighPct": -26.56,
      "aboveLowPct": 97.41,
      "strengthScore": 82.8,
      "momentumScore": 92.8,
      "bias": "Bullish Momentum",
      "rank": 3
    },
    {
      "symbol": "SAREGAMA",
      "stockName": "Saregama India Ltd",
      "indices": [
        "NIFTY MEDIA"
      ],
      "cmp": 498.5,
      "changePct": 4.03,
      "downFromHighPct": -4.13,
      "aboveLowPct": 62.35,
      "strengthScore": 83.8,
      "momentumScore": 91.9,
      "bias": "Bullish Momentum",
      "rank": 4
    },
    {
      "symbol": "BHARATFORG",
      "stockName": "Bharat Forge Ltd.",
      "indices": [
        "NIFTY AUTO",
        "NIFTY INFRA",
        "NIFTY MIDCAP 50"
      ],
      "cmp": 2145.6,
      "changePct": 1.35,
      "downFromHighPct": -4.13,
      "aboveLowPct": 94.97,
      "strengthScore": 88.9,
      "momentumScore": 91.6,
      "bias": "Bullish Momentum",
      "rank": 5
    },
    {
      "symbol": "LAURUSLABS",
      "stockName": "Laurus Labs Ltd.",
      "indices": [
        "NIFTY MIDCAP 50",
        "NIFTY PHARMA"
      ],
      "cmp": 1558.6,
      "changePct": 1.35,
      "downFromHighPct": -0.43,
      "aboveLowPct": 97.74,
      "strengthScore": 88.1,
      "momentumScore": 90.8,
      "bias": "Bullish Momentum",
      "rank": 6
    },
    {
      "symbol": "UNIONBANK",
      "stockName": "Union Bank of India",
      "indices": [
        "NIFTY 100",
        "NIFTY BANK",
        "NIFTY NEXT 50",
        "NIFTY PSU BANK"
      ],
      "cmp": 170.39,
      "changePct": 3.57,
      "downFromHighPct": -17.08,
      "aboveLowPct": 36.71,
      "strengthScore": 81.7,
      "momentumScore": 88.8,
      "bias": "Bullish Momentum",
      "rank": 7
    },
    {
      "symbol": "PAYTM",
      "stockName": "One 97 Communications Ltd.",
      "indices": [
        "NIFTY MIDCAP 50"
      ],
      "cmp": 1386.5,
      "changePct": 3.33,
      "downFromHighPct": -0.78,
      "aboveLowPct": 48.99,
      "strengthScore": 81.5,
      "momentumScore": 88.2,
      "bias": "Bullish Momentum",
      "rank": 8
    },
    {
      "symbol": "BAJAJ-AUTO",
      "stockName": "Bajaj Auto Ltd.",
      "indices": [
        "NIFTY 100",
        "NIFTY 50",
        "NIFTY AUTO"
      ],
      "cmp": 10381.0,
      "changePct": 2.22,
      "downFromHighPct": -4.18,
      "aboveLowPct": 32.1,
      "strengthScore": 81.2,
      "momentumScore": 85.6,
      "bias": "Bullish Momentum",
      "rank": 9
    },
    {
      "symbol": "LLOYDSME",
      "stockName": "Lloyds Metals And Energy Ltd.",
      "indices": [
        "NIFTY METAL"
      ],
      "cmp": 1827.1,
      "changePct": 1.53,
      "downFromHighPct": -3.26,
      "aboveLowPct": 75.19,
      "strengthScore": 82.2,
      "momentumScore": 85.3,
      "bias": "Bullish Momentum",
      "rank": 10
    },
    {
      "symbol": "HCLTECH",
      "stockName": "HCL Technologies Ltd",
      "indices": [
        "NIFTY 100",
        "NIFTY 50",
        "NIFTY IT",
        "S&P BSE SENSEX"
      ],
      "cmp": 1221.2,
      "changePct": 4.91,
      "downFromHighPct": -31.4,
      "aboveLowPct": 18.56,
      "strengthScore": 74.3,
      "momentumScore": 84.1,
      "bias": "Bullish Momentum",
      "rank": 11
    },
    {
      "symbol": "TECHM",
      "stockName": "Tech Mahindra Ltd",
      "indices": [
        "NIFTY 100",
        "NIFTY 50",
        "NIFTY IT",
        "S&P BSE SENSEX"
      ],
      "cmp": 1504.5,
      "changePct": 3.42,
      "downFromHighPct": -18.85,
      "aboveLowPct": 15.37,
      "strengthScore": 77.0,
      "momentumScore": 83.8,
      "bias": "Bullish Momentum",
      "rank": 12
    },
    {
      "symbol": "AJANTPHARM",
      "stockName": "Ajanta Pharmaceuticals Ltd.",
      "indices": [
        "NIFTY PHARMA"
      ],
      "cmp": 3421.4,
      "changePct": 2.17,
      "downFromHighPct": -2.44,
      "aboveLowPct": 46.85,
      "strengthScore": 79.3,
      "momentumScore": 83.6,
      "bias": "Bullish Momentum",
      "rank": 13
    },
    {
      "symbol": "IPCALAB",
      "stockName": "Ipca Laboratories Ltd.",
      "indices": [
        "NIFTY PHARMA"
      ],
      "cmp": 1823.3,
      "changePct": 1.98,
      "downFromHighPct": -0.83,
      "aboveLowPct": 45.68,
      "strengthScore": 78.9,
      "momentumScore": 82.9,
      "bias": "Bullish Momentum",
      "rank": 14
    },
    {
      "symbol": "TCS",
      "stockName": "Tata Consultancy Services Ltd",
      "indices": [
        "NIFTY 100",
        "NIFTY 50",
        "NIFTY IT",
        "S&P BSE SENSEX"
      ],
      "cmp": 2181.5,
      "changePct": 5.44,
      "downFromHighPct": -34.88,
      "aboveLowPct": 10.36,
      "strengthScore": 72.0,
      "momentumScore": 82.9,
      "bias": "Bullish Momentum",
      "rank": 15
    },
    {
      "symbol": "TORNTPHARM",
      "stockName": "Torrent Pharmaceuticals Ltd.",
      "indices": [
        "NIFTY 100",
        "NIFTY NEXT 50",
        "NIFTY PHARMA"
      ],
      "cmp": 4951.1,
      "changePct": 1.01,
      "downFromHighPct": -0.44,
      "aboveLowPct": 49.39,
      "strengthScore": 80.7,
      "momentumScore": 82.7,
      "bias": "Bullish Momentum",
      "rank": 16
    },
    {
      "symbol": "BANDHANBNK",
      "stockName": "Bandhan Bank Ltd.",
      "indices": [
        "NIFTY PVT BANK"
      ],
      "cmp": 213.15,
      "changePct": 1.5,
      "downFromHighPct": -2.28,
      "aboveLowPct": 58.77,
      "strengthScore": 79.2,
      "momentumScore": 82.2,
      "bias": "Bullish Momentum",
      "rank": 17
    },
    {
      "symbol": "WOCKPHARMA",
      "stockName": "Wockhardt Ltd.",
      "indices": [
        "NIFTY PHARMA"
      ],
      "cmp": 1854.5,
      "changePct": 2.42,
      "downFromHighPct": -23.44,
      "aboveLowPct": 70.65,
      "strengthScore": 76.8,
      "momentumScore": 81.6,
      "bias": "Bullish Momentum",
      "rank": 18
    },
    {
      "symbol": "COFORGE",
      "stockName": "Coforge Ltd.",
      "indices": [
        "NIFTY IT",
        "NIFTY MIDCAP 50"
      ],
      "cmp": 1540.9,
      "changePct": 2.47,
      "downFromHighPct": -22.56,
      "aboveLowPct": 52.85,
      "strengthScore": 76.6,
      "momentumScore": 81.5,
      "bias": "Bullish Momentum",
      "rank": 19
    },
    {
      "symbol": "DIVISLAB",
      "stockName": "Divi's Laboratories Ltd.",
      "indices": [
        "NIFTY 100",
        "NIFTY NEXT 50",
        "NIFTY PHARMA"
      ],
      "cmp": 6938.5,
      "changePct": 1.5,
      "downFromHighPct": -0.42,
      "aboveLowPct": 23.1,
      "strengthScore": 78.4,
      "momentumScore": 81.4,
      "bias": "Bullish Momentum",
      "rank": 20
    },
    {
      "symbol": "TVSMOTOR",
      "stockName": "TVS Motor Company Ltd.",
      "indices": [
        "NIFTY 100",
        "NIFTY AUTO",
        "NIFTY NEXT 50"
      ],
      "cmp": 3676.9,
      "changePct": 1.48,
      "downFromHighPct": -7.38,
      "aboveLowPct": 34.75,
      "strengthScore": 78.0,
      "momentumScore": 81.0,
      "bias": "Bullish Momentum",
      "rank": 21
    },
    {
      "symbol": "GMRAIRPORT",
      "stockName": "GMR Airports Ltd.",
      "indices": [
        "NIFTY MIDCAP 50"
      ],
      "cmp": 114.68,
      "changePct": 1.93,
      "downFromHighPct": -0.83,
      "aboveLowPct": 36.35,
      "strengthScore": 77.1,
      "momentumScore": 81.0,
      "bias": "Bullish Momentum",
      "rank": 22
    },
    {
      "symbol": "NTPC",
      "stockName": "NTPC Ltd",
      "indices": [
        "NIFTY 100",
        "NIFTY 50",
        "NIFTY COMMODITIES",
        "NIFTY ENERGY",
        "NIFTY INFRA",
        "S&P BSE SENSEX"
      ],
      "cmp": 351.75,
      "changePct": 2.09,
      "downFromHighPct": -15.12,
      "aboveLowPct": 11.47,
      "strengthScore": 75.8,
      "momentumScore": 80.0,
      "bias": "Bullish Momentum",
      "rank": 23
    },
    {
      "symbol": "ZEEL",
      "stockName": "Zee Entertainment Enterprises Ltd.",
      "indices": [
        "NIFTY MEDIA"
      ],
      "cmp": 101.33,
      "changePct": 3.96,
      "downFromHighPct": -31.06,
      "aboveLowPct": 49.01,
      "strengthScore": 72.1,
      "momentumScore": 80.0,
      "bias": "Bullish Momentum",
      "rank": 24
    },
    {
      "symbol": "GODREJPROP",
      "stockName": "Godrej Properties Ltd.",
      "indices": [
        "NIFTY MIDCAP 50",
        "NIFTY REALTY"
      ],
      "cmp": 2162.6,
      "changePct": 1.39,
      "downFromHighPct": -10.19,
      "aboveLowPct": 50.81,
      "strengthScore": 76.7,
      "momentumScore": 79.5,
      "bias": "Bullish Momentum",
      "rank": 25
    },
    {
      "symbol": "KOTAKBANK",
      "stockName": "Kotak Mahindra Bank Ltd",
      "indices": [
        "FINNIFTY",
        "NIFTY 100",
        "NIFTY 50",
        "NIFTY BANK",
        "NIFTY FINANCIAL SERVICES",
        "NIFTY PVT BANK"
      ],
      "cmp": 384.65,
      "changePct": 1.87,
      "downFromHighPct": -15.13,
      "aboveLowPct": 11.33,
      "strengthScore": 74.9,
      "momentumScore": 78.6,
      "bias": "Bullish Momentum",
      "rank": 26
    },
    {
      "symbol": "JBCHEPHARM",
      "stockName": "J.B. Chemicals & Pharmaceuticals Ltd.",
      "indices": [
        "NIFTY PHARMA"
      ],
      "cmp": 2460.0,
      "changePct": 1.01,
      "downFromHighPct": -0.57,
      "aboveLowPct": 53.37,
      "strengthScore": 76.4,
      "momentumScore": 78.4,
      "bias": "Bullish Momentum",
      "rank": 27
    },
    {
      "symbol": "PERSISTENT",
      "stockName": "Persistent Systems Ltd.",
      "indices": [
        "NIFTY IT",
        "NIFTY MIDCAP 50"
      ],
      "cmp": 5192.4,
      "changePct": 2.74,
      "downFromHighPct": -21.32,
      "aboveLowPct": 22.33,
      "strengthScore": 71.7,
      "momentumScore": 77.2,
      "bias": "Bullish Momentum",
      "rank": 28
    },
    {
      "symbol": "MPHASIS",
      "stockName": "MphasiS Ltd.",
      "indices": [
        "NIFTY IT",
        "NIFTY MIDCAP 50"
      ],
      "cmp": 2390.4,
      "changePct": 2.95,
      "downFromHighPct": -21.3,
      "aboveLowPct": 18.75,
      "strengthScore": 71.2,
      "momentumScore": 77.1,
      "bias": "Bullish Momentum",
      "rank": 29
    },
    {
      "symbol": "INFY",
      "stockName": "Infosys Ltd",
      "indices": [
        "NIFTY 100",
        "NIFTY 50",
        "NIFTY IT",
        "S&P BSE SENSEX"
      ],
      "cmp": 1102.6,
      "changePct": 3.24,
      "downFromHighPct": -36.19,
      "aboveLowPct": 12.24,
      "strengthScore": 70.1,
      "momentumScore": 76.6,
      "bias": "Bullish Momentum",
      "rank": 30
    },
    {
      "symbol": "POWERGRID",
      "stockName": "Power Grid Corporation of India Ltd",
      "indices": [
        "NIFTY 100",
        "NIFTY 50",
        "NIFTY ENERGY",
        "NIFTY INFRA",
        "S&P BSE SENSEX"
      ],
      "cmp": 286.0,
      "changePct": 1.02,
      "downFromHighPct": -11.99,
      "aboveLowPct": 14.4,
      "strengthScore": 73.3,
      "momentumScore": 75.3,
      "bias": "Bullish Momentum",
      "rank": 31
    },
    {
      "symbol": "ONGC",
      "stockName": "Oil & Natural Gas Corporation Ltd.",
      "indices": [
        "NIFTY 100",
        "NIFTY 50",
        "NIFTY COMMODITIES",
        "NIFTY ENERGY",
        "NIFTY INFRA"
      ],
      "cmp": 248.45,
      "changePct": 1.42,
      "downFromHighPct": -19.2,
      "aboveLowPct": 9.14,
      "strengthScore": 71.5,
      "momentumScore": 74.3,
      "bias": "Bullish Momentum",
      "rank": 32
    },
    {
      "symbol": "POLYCAB",
      "stockName": "Polycab India Ltd.",
      "indices": [
        "NIFTY MIDCAP 50"
      ],
      "cmp": 9306.5,
      "changePct": 1.04,
      "downFromHighPct": -8.09,
      "aboveLowPct": 40.58,
      "strengthScore": 72.0,
      "momentumScore": 74.1,
      "bias": "Bullish Momentum",
      "rank": 33
    },
    {
      "symbol": "ASHOKLEY",
      "stockName": "Ashok Leyland Ltd.",
      "indices": [
        "NIFTY AUTO",
        "NIFTY INFRA",
        "NIFTY MIDCAP 50"
      ],
      "cmp": 159.22,
      "changePct": 1.1,
      "downFromHighPct": -26.09,
      "aboveLowPct": 38.5,
      "strengthScore": 70.7,
      "momentumScore": 72.9,
      "bias": "Bullish Momentum",
      "rank": 34
    },
    {
      "symbol": "OIL",
      "stockName": "Oil India Ltd.",
      "indices": [
        "NIFTY COMMODITIES",
        "NIFTY ENERGY",
        "NIFTY MIDCAP 50"
      ],
      "cmp": 431.05,
      "changePct": 1.44,
      "downFromHighPct": -18.82,
      "aboveLowPct": 12.08,
      "strengthScore": 69.8,
      "momentumScore": 72.7,
      "bias": "Bullish Momentum",
      "rank": 35
    },
    {
      "symbol": "TORNTPOWER",
      "stockName": "Torrent Power Ltd.",
      "indices": [
        "NIFTY COMMODITIES",
        "NIFTY ENERGY"
      ],
      "cmp": 1441.9,
      "changePct": 1.59,
      "downFromHighPct": -20.95,
      "aboveLowPct": 21.37,
      "strengthScore": 69.2,
      "momentumScore": 72.4,
      "bias": "Bullish Momentum",
      "rank": 36
    },
    {
      "symbol": "LTM",
      "stockName": "LTM Ltd.",
      "indices": [
        "NIFTY 100",
        "NIFTY IT",
        "NIFTY NEXT 50"
      ],
      "cmp": 4124.3,
      "changePct": 2.16,
      "downFromHighPct": -35.85,
      "aboveLowPct": 16.9,
      "strengthScore": 67.4,
      "momentumScore": 71.7,
      "bias": "Bullish Momentum",
      "rank": 37
    },
    {
      "symbol": "PVRINOX",
      "stockName": "PVR INOX Ltd.",
      "indices": [
        "NIFTY MEDIA"
      ],
      "cmp": 1020.55,
      "changePct": 1.85,
      "downFromHighPct": -18.34,
      "aboveLowPct": 12.47,
      "strengthScore": 66.3,
      "momentumScore": 70.0,
      "bias": "Bullish Momentum",
      "rank": 38
    },
    {
      "symbol": "HDFCLIFE",
      "stockName": "HDFC Life Insurance Company Ltd.",
      "indices": [
        "FINNIFTY",
        "NIFTY 100",
        "NIFTY 50",
        "NIFTY FINANCIAL SERVICES"
      ],
      "cmp": 573.4,
      "changePct": 1.0,
      "downFromHighPct": -29.64,
      "aboveLowPct": 5.6,
      "strengthScore": 65.2,
      "momentumScore": 67.2,
      "bias": "Bullish Momentum",
      "rank": 39
    },
    {
      "symbol": "INOXWIND",
      "stockName": "Inox Wind Ltd.",
      "indices": [
        "NIFTY ENERGY"
      ],
      "cmp": 81.09,
      "changePct": -1.84,
      "downFromHighPct": -54.39,
      "aboveLowPct": 8.05,
      "strengthScore": 22.4,
      "momentumScore": 81.3,
      "bias": "Bearish Momentum",
      "rank": 40
    },
    {
      "symbol": "SWIGGY",
      "stockName": "Swiggy Ltd.",
      "indices": [
        "NIFTY MIDCAP 50"
      ],
      "cmp": 266.77,
      "changePct": -2.37,
      "downFromHighPct": -43.72,
      "aboveLowPct": 13.16,
      "strengthScore": 24.9,
      "momentumScore": 79.8,
      "bias": "Bearish Momentum",
      "rank": 41
    },
    {
      "symbol": "PIIND",
      "stockName": "PI Industries Ltd.",
      "indices": [
        "NIFTY COMMODITIES"
      ],
      "cmp": 2569.0,
      "changePct": -1.47,
      "downFromHighPct": -40.67,
      "aboveLowPct": 1.1,
      "strengthScore": 27.6,
      "momentumScore": 75.3,
      "bias": "Bearish Momentum",
      "rank": 42
    },
    {
      "symbol": "VEDL",
      "stockName": "Vedanta Ltd.",
      "indices": [
        "NIFTY 100",
        "NIFTY COMMODITIES",
        "NIFTY METAL",
        "NIFTY NEXT 50"
      ],
      "cmp": 269.65,
      "changePct": -1.06,
      "downFromHighPct": -66.08,
      "aboveLowPct": 0.58,
      "strengthScore": 29.9,
      "momentumScore": 72.2,
      "bias": "Bearish Momentum",
      "rank": 43
    },
    {
      "symbol": "PATANJALI",
      "stockName": "Patanjali Foods Ltd.",
      "indices": [
        "NIFTY FMCG"
      ],
      "cmp": 408.85,
      "changePct": -1.2,
      "downFromHighPct": -37.48,
      "aboveLowPct": 0.62,
      "strengthScore": 30.3,
      "momentumScore": 72.1,
      "bias": "Bearish Momentum",
      "rank": 44
    },
    {
      "symbol": "NLCINDIA",
      "stockName": "NLC India Ltd.",
      "indices": [
        "NIFTY ENERGY"
      ],
      "cmp": 304.65,
      "changePct": -3.26,
      "downFromHighPct": -21.44,
      "aboveLowPct": 37.23,
      "strengthScore": 36.1,
      "momentumScore": 70.4,
      "bias": "Bearish Momentum",
      "rank": 45
    },
    {
      "symbol": "JSL",
      "stockName": "Jindal Stainless Ltd.",
      "indices": [
        "NIFTY METAL"
      ],
      "cmp": 703.35,
      "changePct": -1.82,
      "downFromHighPct": -20.44,
      "aboveLowPct": 7.83,
      "strengthScore": 34.3,
      "momentumScore": 69.3,
      "bias": "Bearish Momentum",
      "rank": 46
    },
    {
      "symbol": "JPPOWER",
      "stockName": "Jaiprakash Power Ventures Ltd.",
      "indices": [
        "NIFTY ENERGY"
      ],
      "cmp": 16.79,
      "changePct": -1.35,
      "downFromHighPct": -39.39,
      "aboveLowPct": 27.68,
      "strengthScore": 33.5,
      "momentumScore": 69.2,
      "bias": "Bearish Momentum",
      "rank": 47
    },
    {
      "symbol": "DMART",
      "stockName": "Avenue Supermarts Ltd.",
      "indices": [
        "NIFTY 100",
        "NIFTY NEXT 50"
      ],
      "cmp": 3994.1,
      "changePct": -2.13,
      "downFromHighPct": -19.3,
      "aboveLowPct": 10.95,
      "strengthScore": 36.0,
      "momentumScore": 68.3,
      "bias": "Bearish Momentum",
      "rank": 48
    },
    {
      "symbol": "INDIANB",
      "stockName": "Indian Bank",
      "indices": [
        "NIFTY PSU BANK"
      ],
      "cmp": 842.55,
      "changePct": -3.23,
      "downFromHighPct": -15.82,
      "aboveLowPct": 39.03,
      "strengthScore": 38.7,
      "momentumScore": 67.8,
      "bias": "Bearish Momentum",
      "rank": 49
    },
    {
      "symbol": "PPLPHARMA",
      "stockName": "Piramal Pharma Ltd.",
      "indices": [
        "NIFTY PHARMA"
      ],
      "cmp": 173.63,
      "changePct": -1.99,
      "downFromHighPct": -21.38,
      "aboveLowPct": 31.24,
      "strengthScore": 37.3,
      "momentumScore": 66.7,
      "bias": "Bearish Momentum",
      "rank": 50
    },
    {
      "symbol": "WAAREEENER",
      "stockName": "Waaree Energies Ltd.",
      "indices": [
        "NIFTY MIDCAP 50"
      ],
      "cmp": 2880.2,
      "changePct": -1.46,
      "downFromHighPct": -25.48,
      "aboveLowPct": 19.86,
      "strengthScore": 36.3,
      "momentumScore": 66.6,
      "bias": "Bearish Momentum",
      "rank": 51
    },
    {
      "symbol": "IOB",
      "stockName": "Indian Overseas Bank",
      "indices": [
        "NIFTY PSU BANK"
      ],
      "cmp": 34.15,
      "changePct": -1.24,
      "downFromHighPct": -18.3,
      "aboveLowPct": 9.46,
      "strengthScore": 37.9,
      "momentumScore": 64.6,
      "bias": "Bearish Momentum",
      "rank": 52
    },
    {
      "symbol": "MUTHOOTFIN",
      "stockName": "Muthoot Finance Ltd.",
      "indices": [
        "FINNIFTY",
        "NIFTY 100",
        "NIFTY FINANCIAL SERVICES",
        "NIFTY NEXT 50"
      ],
      "cmp": 3058.5,
      "changePct": -2.27,
      "downFromHighPct": -26.29,
      "aboveLowPct": 23.5,
      "strengthScore": 40.3,
      "momentumScore": 64.2,
      "bias": "Bearish Momentum",
      "rank": 53
    },
    {
      "symbol": "ICICIGI",
      "stockName": "ICICI Lombard General Insurance Company Ltd.",
      "indices": [
        "FINNIFTY",
        "NIFTY FINANCIAL SERVICES",
        "NIFTY MIDCAP 50"
      ],
      "cmp": 1787.3,
      "changePct": -2.13,
      "downFromHighPct": -13.44,
      "aboveLowPct": 9.68,
      "strengthScore": 40.2,
      "momentumScore": 64.1,
      "bias": "Bearish Momentum",
      "rank": 54
    },
    {
      "symbol": "JINDALSTEL",
      "stockName": "Jindal Steel Ltd.",
      "indices": [
        "NIFTY 100",
        "NIFTY COMMODITIES",
        "NIFTY METAL",
        "NIFTY NEXT 50"
      ],
      "cmp": 1028.8,
      "changePct": -2.14,
      "downFromHighPct": -21.24,
      "aboveLowPct": 10.96,
      "strengthScore": 40.2,
      "momentumScore": 64.1,
      "bias": "Bearish Momentum",
      "rank": 55
    },
    {
      "symbol": "CESC",
      "stockName": "CESC Ltd.",
      "indices": [
        "NIFTY ENERGY"
      ],
      "cmp": 161.92,
      "changePct": -1.23,
      "downFromHighPct": -20.82,
      "aboveLowPct": 17.23,
      "strengthScore": 38.7,
      "momentumScore": 63.8,
      "bias": "Bearish Momentum",
      "rank": 56
    },
    {
      "symbol": "GODREJCP",
      "stockName": "Godrej Consumer Products Ltd.",
      "indices": [
        "NIFTY 100",
        "NIFTY FMCG",
        "NIFTY NEXT 50"
      ],
      "cmp": 1068.7,
      "changePct": -1.81,
      "downFromHighPct": -18.36,
      "aboveLowPct": 10.51,
      "strengthScore": 40.7,
      "momentumScore": 62.9,
      "bias": "Bearish Momentum",
      "rank": 57
    },
    {
      "symbol": "MGL",
      "stockName": "Mahanagar Gas Ltd.",
      "indices": [
        "NIFTY ENERGY"
      ],
      "cmp": 1114.4,
      "changePct": -1.06,
      "downFromHighPct": -28.66,
      "aboveLowPct": 23.82,
      "strengthScore": 39.3,
      "momentumScore": 62.8,
      "bias": "Bearish Momentum",
      "rank": 58
    },
    {
      "symbol": "COLPAL",
      "stockName": "Colgate Palmolive (India) Ltd.",
      "indices": [
        "NIFTY FMCG",
        "NIFTY MIDCAP 50"
      ],
      "cmp": 2025.0,
      "changePct": -1.34,
      "downFromHighPct": -19.13,
      "aboveLowPct": 13.64,
      "strengthScore": 40.6,
      "momentumScore": 62.1,
      "bias": "Bearish Momentum",
      "rank": 59
    },
    {
      "symbol": "UNOMINDA",
      "stockName": "UNO Minda Ltd.",
      "indices": [
        "NIFTY AUTO"
      ],
      "cmp": 1152.3,
      "changePct": -1.18,
      "downFromHighPct": -16.62,
      "aboveLowPct": 15.93,
      "strengthScore": 40.9,
      "momentumScore": 61.5,
      "bias": "Bearish Momentum",
      "rank": 60
    },
    {
      "symbol": "ETERNAL",
      "stockName": "Eternal Ltd.",
      "indices": [
        "NIFTY 100",
        "NIFTY 50"
      ],
      "cmp": 285.2,
      "changePct": -1.54,
      "downFromHighPct": -22.59,
      "aboveLowPct": 34.15,
      "strengthScore": 42.0,
      "momentumScore": 61.1,
      "bias": "Bearish Momentum",
      "rank": 61
    },
    {
      "symbol": "DABUR",
      "stockName": "Dabur India Ltd.",
      "indices": [
        "NIFTY FMCG",
        "NIFTY MIDCAP 50"
      ],
      "cmp": 438.9,
      "changePct": -1.04,
      "downFromHighPct": -23.93,
      "aboveLowPct": 8.81,
      "strengthScore": 41.0,
      "momentumScore": 61.1,
      "bias": "Bearish Momentum",
      "rank": 62
    },
    {
      "symbol": "BIOCON",
      "stockName": "Biocon Ltd.",
      "indices": [
        "NIFTY PHARMA"
      ],
      "cmp": 410.95,
      "changePct": -1.8,
      "downFromHighPct": -6.69,
      "aboveLowPct": 24.15,
      "strengthScore": 42.6,
      "momentumScore": 61.0,
      "bias": "Bearish Momentum",
      "rank": 63
    },
    {
      "symbol": "VBL",
      "stockName": "Varun Beverages Ltd.",
      "indices": [
        "NIFTY 100",
        "NIFTY FMCG",
        "NIFTY NEXT 50"
      ],
      "cmp": 469.1,
      "changePct": -1.88,
      "downFromHighPct": -15.6,
      "aboveLowPct": 23.12,
      "strengthScore": 43.2,
      "momentumScore": 60.6,
      "bias": "Bearish Momentum",
      "rank": 64
    },
    {
      "symbol": "TATASTEEL",
      "stockName": "Tata Steel Ltd",
      "indices": [
        "NIFTY 100",
        "NIFTY 50",
        "NIFTY COMMODITIES",
        "NIFTY METAL",
        "S&P BSE SENSEX"
      ],
      "cmp": 187.11,
      "changePct": -2.13,
      "downFromHighPct": -16.62,
      "aboveLowPct": 22.69,
      "strengthScore": 44.0,
      "momentumScore": 60.3,
      "bias": "Bearish Momentum",
      "rank": 65
    },
    {
      "symbol": "ALKEM",
      "stockName": "Alkem Laboratories Ltd.",
      "indices": [
        "NIFTY MIDCAP 50",
        "NIFTY PHARMA"
      ],
      "cmp": 5567.0,
      "changePct": -1.81,
      "downFromHighPct": -6.18,
      "aboveLowPct": 17.48,
      "strengthScore": 43.5,
      "momentumScore": 60.1,
      "bias": "Bearish Momentum",
      "rank": 66
    },
    {
      "symbol": "NAUKRI",
      "stockName": "Info Edge (India) Ltd.",
      "indices": [
        "NIFTY MIDCAP 50"
      ],
      "cmp": 1191.05,
      "changePct": -1.08,
      "downFromHighPct": -19.79,
      "aboveLowPct": 31.13,
      "strengthScore": 43.3,
      "momentumScore": 58.9,
      "bias": "Bearish Momentum",
      "rank": 67
    },
    {
      "symbol": "SRF",
      "stockName": "SRF Ltd.",
      "indices": [
        "NIFTY COMMODITIES",
        "NIFTY MIDCAP 50"
      ],
      "cmp": 2741.6,
      "changePct": -1.19,
      "downFromHighPct": -15.91,
      "aboveLowPct": 16.42,
      "strengthScore": 43.6,
      "momentumScore": 58.8,
      "bias": "Bearish Momentum",
      "rank": 68
    },
    {
      "symbol": "TATACONSUM",
      "stockName": "Tata Consumer Products Ltd.",
      "indices": [
        "NIFTY 100",
        "NIFTY 50",
        "NIFTY FMCG"
      ],
      "cmp": 1098.6,
      "changePct": -1.2,
      "downFromHighPct": -14.35,
      "aboveLowPct": 9.07,
      "strengthScore": 44.7,
      "momentumScore": 57.7,
      "bias": "Bearish Momentum",
      "rank": 69
    },
    {
      "symbol": "ADANIPOWER",
      "stockName": "Adani Power Ltd.",
      "indices": [
        "NIFTY 100",
        "NIFTY COMMODITIES",
        "NIFTY ENERGY",
        "NIFTY NEXT 50"
      ],
      "cmp": 215.46,
      "changePct": -1.37,
      "downFromHighPct": -15.24,
      "aboveLowPct": 95.07,
      "strengthScore": 61.2,
      "momentumScore": 57.7,
      "bias": "Pullback Watch",
      "rank": 70
    },
    {
      "symbol": "CGPOWER",
      "stockName": "CG Power and Industrial Solutions Ltd.",
      "indices": [
        "NIFTY 100",
        "NIFTY ENERGY",
        "NIFTY INFRA",
        "NIFTY NEXT 50"
      ],
      "cmp": 905.5,
      "changePct": -1.21,
      "downFromHighPct": -7.69,
      "aboveLowPct": 72.31,
      "strengthScore": 60.7,
      "momentumScore": 57.4,
      "bias": "Pullback Watch",
      "rank": 71
    },
    {
      "symbol": "CUMMINSIND",
      "stockName": "Cummins India Ltd.",
      "indices": [
        "NIFTY 100",
        "NIFTY INFRA",
        "NIFTY NEXT 50"
      ],
      "cmp": 5555.0,
      "changePct": -1.18,
      "downFromHighPct": -8.93,
      "aboveLowPct": 60.32,
      "strengthScore": 56.5,
      "momentumScore": 57.4,
      "bias": "Pullback Watch",
      "rank": 72
    },
    {
      "symbol": "AUBANK",
      "stockName": "AU Small Finance Bank Ltd.",
      "indices": [
        "NIFTY BANK",
        "NIFTY MIDCAP 50"
      ],
      "cmp": 1060.5,
      "changePct": -1.08,
      "downFromHighPct": -2.74,
      "aboveLowPct": 55.46,
      "strengthScore": 55.9,
      "momentumScore": 57.2,
      "bias": "Pullback Watch",
      "rank": 73
    }
  ]
}