{
  "updatedAt": "17-Jun-2026 14:55 IST",
  "sourceNote": "Generated by hybrid script using NSE/Yahoo with previous JSON fallback. Values may be delayed.",
  "indices": [
    {
      "name": "NIFTY 50",
      "value": 24085.7,
      "change": 96.55,
      "changePct": 0.4,
      "source": "NSE"
    },
    {
      "name": "BANK NIFTY",
      "value": 57585.05,
      "change": 287.9,
      "changePct": 0.5,
      "source": "NSE"
    },
    {
      "name": "MIDCAP SELECT",
      "value": 14575.8,
      "change": 71.9,
      "changePct": 0.5,
      "source": "NSE"
    },
    {
      "name": "INDIA VIX",
      "value": 13.19,
      "change": -0.17,
      "changePct": -1.3,
      "source": "NSE"
    }
  ]
}