{
  "indexName": "NIFTY PSU BANK",
  "slug": "nifty-psu-bank",
  "updatedAt": "23-Jul-2026 15:55 IST",
  "sourceNote": "Generated by Automation In Trade hybrid script. Primary source: NSE India live index/quote APIs; Yahoo Finance is used only as fallback; previous JSON is used only when all live sources fail or look suspicious. Values may be delayed. Educational use only.",
  "stocks": [
    {
      "symbol": "PSB",
      "stockName": "Punjab & Sind Bank",
      "high52": 32.46,
      "low52": 20.5,
      "cmp": 24.14,
      "changePct": -1.19,
      "source": "Yahoo",
      "dataQuality": "OK",
      "downFromHighPct": -25.63,
      "aboveLowPct": 17.76,
      "status": "Corrected"
    },
    {
      "symbol": "BANKBARODA",
      "stockName": "Bank of Baroda",
      "high52": 325.5,
      "low52": 230.81,
      "cmp": 243.15,
      "changePct": -1.06,
      "source": "Yahoo",
      "dataQuality": "OK",
      "downFromHighPct": -25.3,
      "aboveLowPct": 5.35,
      "status": "Corrected"
    },
    {
      "symbol": "CENTRALBK",
      "stockName": "Central Bank of India",
      "high52": 40.92,
      "low52": 29.32,
      "cmp": 30.95,
      "changePct": -0.74,
      "source": "Yahoo",
      "dataQuality": "OK",
      "downFromHighPct": -24.36,
      "aboveLowPct": 5.56,
      "status": "Corrected"
    },
    {
      "symbol": "UCOBANK",
      "stockName": "UCO Bank",
      "high52": 34.2,
      "low52": 22.22,
      "cmp": 26.0,
      "changePct": -2.07,
      "source": "Yahoo",
      "dataQuality": "OK",
      "downFromHighPct": -23.98,
      "aboveLowPct": 17.01,
      "status": "Corrected"
    },
    {
      "symbol": "CANBK",
      "stockName": "Canara Bank",
      "high52": 162.89,
      "low52": 103.55,
      "cmp": 125.22,
      "changePct": -0.98,
      "source": "Yahoo",
      "dataQuality": "OK",
      "downFromHighPct": -23.13,
      "aboveLowPct": 20.93,
      "status": "Corrected"
    },
    {
      "symbol": "BANKINDIA",
      "stockName": "Bank of India",
      "high52": 178.36,
      "low52": 108.81,
      "cmp": 142.2,
      "changePct": -1.24,
      "source": "Yahoo",
      "dataQuality": "OK",
      "downFromHighPct": -20.27,
      "aboveLowPct": 30.69,
      "status": "Corrected"
    },
    {
      "symbol": "IOB",
      "stockName": "Indian Overseas Bank",
      "high52": 41.8,
      "low52": 31.2,
      "cmp": 33.82,
      "changePct": -2.23,
      "source": "Yahoo",
      "dataQuality": "OK",
      "downFromHighPct": -19.09,
      "aboveLowPct": 8.4,
      "status": "Corrected"
    },
    {
      "symbol": "PNB",
      "stockName": "Punjab National Bank",
      "high52": 135.15,
      "low52": 98.5,
      "cmp": 110.15,
      "changePct": -0.52,
      "source": "Yahoo",
      "dataQuality": "OK",
      "downFromHighPct": -18.5,
      "aboveLowPct": 11.83,
      "status": "Corrected"
    },
    {
      "symbol": "UNIONBANK",
      "stockName": "Union Bank of India",
      "high52": 205.49,
      "low52": 124.64,
      "cmp": 168.4,
      "changePct": -1.31,
      "source": "Yahoo",
      "dataQuality": "OK",
      "downFromHighPct": -18.05,
      "aboveLowPct": 35.11,
      "status": "Corrected"
    },
    {
      "symbol": "SBIN",
      "stockName": "State Bank of India",
      "high52": 1234.7,
      "low52": 786.55,
      "cmp": 1012.6,
      "changePct": -1.21,
      "source": "Yahoo",
      "dataQuality": "OK",
      "downFromHighPct": -17.99,
      "aboveLowPct": 28.74,
      "status": "Corrected"
    },
    {
      "symbol": "INDIANB",
      "stockName": "Indian Bank",
      "high52": 1000.9,
      "low52": 606.0,
      "cmp": 827.3,
      "changePct": -0.03,
      "source": "Yahoo",
      "dataQuality": "OK",
      "downFromHighPct": -17.34,
      "aboveLowPct": 36.52,
      "status": "Corrected"
    },
    {
      "symbol": "MAHABANK",
      "stockName": "Bank of Maharashtra",
      "high52": 94.5,
      "low52": 51.71,
      "cmp": 78.48,
      "changePct": -0.87,
      "source": "Yahoo",
      "dataQuality": "OK",
      "downFromHighPct": -16.95,
      "aboveLowPct": 51.77,
      "status": "Corrected"
    }
  ]
}