{
  "indexName": "NIFTY BANK",
  "slug": "nifty-bank",
  "updatedAt": "10-Jul-2026 12:57 IST",
  "sourceNote": "Generated by Automation In Trade hybrid script. Primary source: NSE India live index/quote APIs; Yahoo Finance is used only as fallback; previous JSON is used only when all live sources fail or look suspicious. Values may be delayed. Educational use only.",
  "stocks": [
    {
      "symbol": "BANKBARODA",
      "stockName": "Bank of Baroda",
      "high52": 325.5,
      "low52": 230.81,
      "cmp": 250.95,
      "changePct": 2.6,
      "source": "Yahoo",
      "dataQuality": "OK",
      "downFromHighPct": -22.9,
      "aboveLowPct": 8.73,
      "status": "Corrected"
    },
    {
      "symbol": "PNB",
      "stockName": "Punjab National Bank",
      "high52": 135.15,
      "low52": 98.5,
      "cmp": 105.41,
      "changePct": 1.9,
      "source": "Yahoo",
      "dataQuality": "OK",
      "downFromHighPct": -22.01,
      "aboveLowPct": 7.02,
      "status": "Corrected"
    },
    {
      "symbol": "CANBK",
      "stockName": "Canara Bank",
      "high52": 162.89,
      "low52": 103.55,
      "cmp": 128.78,
      "changePct": 3.19,
      "source": "Yahoo",
      "dataQuality": "OK",
      "downFromHighPct": -20.94,
      "aboveLowPct": 24.37,
      "status": "Corrected"
    },
    {
      "symbol": "UNIONBANK",
      "stockName": "Union Bank of India",
      "high52": 205.49,
      "low52": 124.64,
      "cmp": 164.51,
      "changePct": 4.61,
      "source": "Yahoo",
      "dataQuality": "OK",
      "downFromHighPct": -19.94,
      "aboveLowPct": 31.99,
      "status": "Corrected"
    },
    {
      "symbol": "HDFCBANK",
      "stockName": "HDFC Bank Ltd.",
      "high52": 1020.5,
      "low52": 726.65,
      "cmp": 824.95,
      "changePct": 0.91,
      "source": "Yahoo",
      "dataQuality": "OK",
      "downFromHighPct": -19.16,
      "aboveLowPct": 13.53,
      "status": "Corrected"
    },
    {
      "symbol": "KOTAKBANK",
      "stockName": "Kotak Mahindra Bank Ltd.",
      "high52": 453.2,
      "low52": 345.5,
      "cmp": 377.6,
      "changePct": 0.12,
      "source": "Yahoo",
      "dataQuality": "OK",
      "downFromHighPct": -16.68,
      "aboveLowPct": 9.29,
      "status": "Corrected"
    },
    {
      "symbol": "SBIN",
      "stockName": "State Bank of India",
      "high52": 1234.7,
      "low52": 786.55,
      "cmp": 1036.0,
      "changePct": 1.36,
      "source": "Yahoo",
      "dataQuality": "OK",
      "downFromHighPct": -16.09,
      "aboveLowPct": 31.71,
      "status": "Corrected"
    },
    {
      "symbol": "YESBANK",
      "stockName": "Yes Bank Ltd.",
      "high52": 25.78,
      "low52": 17.2,
      "cmp": 23.94,
      "changePct": 1.27,
      "source": "Yahoo",
      "dataQuality": "OK",
      "downFromHighPct": -7.14,
      "aboveLowPct": 39.19,
      "status": "Mid Range"
    },
    {
      "symbol": "IDFCFIRSTB",
      "stockName": "IDFC First Bank Ltd.",
      "high52": 87.0,
      "low52": 58.08,
      "cmp": 80.83,
      "changePct": 1.72,
      "source": "Yahoo",
      "dataQuality": "OK",
      "downFromHighPct": -7.09,
      "aboveLowPct": 39.17,
      "status": "Mid Range"
    },
    {
      "symbol": "AXISBANK",
      "stockName": "Axis Bank Ltd.",
      "high52": 1418.3,
      "low52": 1042.5,
      "cmp": 1323.7,
      "changePct": 2.01,
      "source": "Yahoo",
      "dataQuality": "OK",
      "downFromHighPct": -6.67,
      "aboveLowPct": 26.97,
      "status": "Mid Range"
    },
    {
      "symbol": "ICICIBANK",
      "stockName": "ICICI Bank Ltd.",
      "high52": 1500.0,
      "low52": 1187.6,
      "cmp": 1401.2,
      "changePct": 1.48,
      "source": "Yahoo",
      "dataQuality": "OK",
      "downFromHighPct": -6.59,
      "aboveLowPct": 17.99,
      "status": "Mid Range"
    },
    {
      "symbol": "INDUSINDBK",
      "stockName": "IndusInd Bank Ltd.",
      "high52": 1038.0,
      "low52": 710.6,
      "cmp": 1015.8,
      "changePct": 0.06,
      "source": "Yahoo",
      "dataQuality": "OK",
      "downFromHighPct": -2.14,
      "aboveLowPct": 42.95,
      "status": "Near 52W High"
    },
    {
      "symbol": "AUBANK",
      "stockName": "AU Small Finance Bank Ltd.",
      "high52": 1090.4,
      "low52": 682.15,
      "cmp": 1072.1,
      "changePct": 2.36,
      "source": "Yahoo",
      "dataQuality": "OK",
      "downFromHighPct": -1.68,
      "aboveLowPct": 57.16,
      "status": "Near 52W High"
    },
    {
      "symbol": "FEDERALBNK",
      "stockName": "Federal Bank Ltd.",
      "high52": 334.3,
      "low52": 185.11,
      "cmp": 329.85,
      "changePct": 0.64,
      "source": "Yahoo",
      "dataQuality": "OK",
      "downFromHighPct": -1.33,
      "aboveLowPct": 78.19,
      "status": "Near 52W High"
    }
  ]
}